{
  "$schema": "https://ui.shadcn.com/schema/registry-item.json",
  "name": "switch-privacy-mode",
  "description": "Switch Privacy Mode example",
  "registryDependencies": [
    "@loveui/switch"
  ],
  "files": [
    {
      "path": "registry/default/examples/switch-privacy-mode.tsx",
      "content": "import { LockIcon } from \"lucide-react\"\n\nimport { Switch } from \"@/registry/default/ui/switch\"\n\nexport default function SwitchPrivacyMode() {\n  return (\n    <label className=\"flex max-w-sm items-center justify-between gap-6 rounded-xl border p-4\">\n      <span className=\"flex items-center gap-3 text-sm font-medium\"><LockIcon className=\"size-4 text-muted-foreground\" /> Private workspace</span>\n      <Switch defaultChecked />\n    </label>\n  )\n}\n",
      "type": "registry:example"
    }
  ],
  "categories": [
    "switch"
  ],
  "type": "registry:example"
}
